pymc3_ext/__init__.py
pymc3_ext/optim.py
pymc3_ext/pymc3_ext_version.py
pymc3_ext/utils.py
pymc3_ext/distributions/__init__.py
pymc3_ext/distributions/base.py
pymc3_ext/distributions/helpers.py
pymc3_ext/distributions/transforms.py
pymc3_ext/sampling/__init__.py
pymc3_ext/sampling/estimator.py
pymc3_ext/sampling/groups.py
pymc3_ext/sampling/quadpotential.py
pymc3_ext/sampling/sampling.py
pymc3_ext/sampling/schedule.py
pymc3_ext/sampling/step_size.py
pymc3_ext-0.1.1.dist-info/LICENSE
pymc3_ext-0.1.1.dist-info/METADATA
pymc3_ext-0.1.1.dist-info/WHEEL
pymc3_ext-0.1.1.dist-info/top_level.txt
pymc3_ext-0.1.1.dist-info/RECORD
