Metadata-Version: 2.1
Name: pymc3-ext
Version: 0.1.1
Summary: PyMC3 Extras extracted from the 
Home-page: https://github.com/exoplanet-dev/pymc3-ext
Author: Daniel Foreman-Mackey
Author-email: foreman.mackey@gmail.com
Maintainer: Daniel Foreman-Mackey
Maintainer-email: foreman.mackey@gmail.com
License: MIT
Platform: UNKNOWN
Classifier: Development Status :: 4 - Beta
Classifier: Intended Audience :: Developers
Classifier: Intended Audience :: Science/Research
Classifier: License :: OSI Approved :: MIT License
Classifier: Operating System :: OS Independent
Classifier: Programming Language :: Python
Classifier: Programming Language :: Python :: 3
Provides-Extra: test
Provides-Extra: notebooks
Provides-Extra: dev
License-File: LICENSE
